{"documentation":"https://opencagedata.com/api","licenses":[{"name":"CC-BY-SA","url":"https://creativecommons.org/licenses/by-sa/3.0/"},{"name":"ODbL","url":"https://opendatacommons.org/licenses/odbl/summary/"}],"rate":{"limit":2500,"remaining":1628,"reset":1538697600},"results":[{"annotations":{"DMS":{"lat":"41° 53' 31.14240'' N","lng":"87° 58' 9.37920'' W"},"FIPS":{"county":"17043","state":"17"},"MGRS":"16TDM1959138237","Maidenhead":"EN61av34qb","Mercator":{"x":-9792694.564,"y":5116274.013},"OSM":{"edit_url":"https://www.openstreetmap.org/edit?way=22089323#map=17/41.89198/-87.96927","url":"https://www.openstreetmap.org/?mlat=41.89198&mlon=-87.96927#map=17/41.89198/-87.96927"},"callingcode":1,"currency":{"alternate_symbols":["US$"],"decimal_mark":".","disambiguate_symbol":"US$","html_entity":"$","iso_code":"USD","iso_numeric":840,"name":"United States Dollar","smallest_denomination":1,"subunit":"Cent","subunit_to_unit":100,"symbol":"$","symbol_first":1,"thousands_separator":","},"flag":"🇺🇸","geohash":"dp3qq4nwrrud3kxkxq6v","qibla":48.41,"sun":{"rise":{"apparent":1538653920,"astronomical":1538648340,"civil":1538652240,"nautical":1538650320},"set":{"apparent":1538695560,"astronomical":1538614740,"civil":1538697240,"nautical":1538612760}},"timezone":{"name":"America/Chicago","now_in_dst":1,"offset_sec":-18000,"offset_string":-500,"short_name":"CDT"},"what3words":{"words":"action.plank.sentences"}},"bounds":{"northeast":{"lat":41.892034,"lng":-87.969222},"southwest":{"lat":41.891934,"lng":-87.969322}},"components":{"ISO_3166-1_alpha-2":"US","_type":"building","country":"USA","country_code":"us","county":"DuPage County","house_number":"126","postcode":"60181","road":"Villa Avenue","state":"Illinois","state_code":"IL","village":"Villa Park"},"confidence":10,"formatted":"126 Villa Avenue, Villa Park, IL 60181, United States of America","geometry":{"lat":41.891984,"lng":-87.969272}},{"annotations":{"DMS":{"lat":"41° 53' 15.78948'' N","lng":"87° 58' 9.37020'' W"},"FIPS":{"county":"17043","state":"17"},"MGRS":"16TDM1958637764","Maidenhead":"EN61av33qb","Mercator":{"x":-9792694.283,"y":5115638.655},"OSM":{"edit_url":"https://www.openstreetmap.org/edit?way=22106877#map=17/41.88772/-87.96927","url":"https://www.openstreetmap.org/?mlat=41.88772&mlon=-87.96927#map=17/41.88772/-87.96927"},"callingcode":1,"currency":{"alternate_symbols":["US$"],"decimal_mark":".","disambiguate_symbol":"US$","html_entity":"$","iso_code":"USD","iso_numeric":840,"name":"United States Dollar","smallest_denomination":1,"subunit":"Cent","subunit_to_unit":100,"symbol":"$","symbol_first":1,"thousands_separator":","},"flag":"🇺🇸","geohash":"dp3qq1qtxky6mu78z2bc","qibla":48.41,"sun":{"rise":{"apparent":1538653920,"astronomical":1538648340,"civil":1538652240,"nautical":1538650320},"set":{"apparent":1538695560,"astronomical":1538614740,"civil":1538697240,"nautical":1538612760}},"timezone":{"name":"America/Chicago","now_in_dst":1,"offset_sec":-18000,"offset_string":-500,"short_name":"CDT"},"what3words":{"words":"sooner.nails.baking"}},"bounds":{"northeast":{"lat":41.8877693,"lng":-87.9692195},"southwest":{"lat":41.8876693,"lng":-87.9693195}},"components":{"ISO_3166-1_alpha-2":"US","_type":"building","country":"USA","country_code":"us","county":"DuPage County","house_number":"126","postcode":"60181","road":"South Villa Avenue","state":"Illinois","state_code":"IL","village":"Villa Park"},"confidence":10,"formatted":"126 South Villa Avenue, Villa Park, IL 60181, United States of America","geometry":{"lat":41.8877193,"lng":-87.9692695}},{"annotations":{"DMS":{"lat":"41° 53' 15.41400'' N","lng":"87° 58' 9.24240'' W"},"MGRS":"16TDM1958837752","Maidenhead":"EN61av33qa","Mercator":{"x":-9792690.334,"y":5115623.119},"OSM":{"url":"https://www.openstreetmap.org/?mlat=41.88761&mlon=-87.96923#map=17/41.88761/-87.96923"},"callingcode":1,"currency":{"alternate_symbols":["US$"],"decimal_mark":".","disambiguate_symbol":"US$","html_entity":"$","iso_code":"USD","iso_numeric":840,"name":"United States Dollar","smallest_denomination":1,"subunit":"Cent","subunit_to_unit":100,"symbol":"$","symbol_first":1,"thousands_separator":","},"flag":"🇺🇸","geohash":"dp3qq1qv032uk1qq5u66","qibla":48.41,"sun":{"rise":{"apparent":1538653920,"astronomical":1538648340,"civil":1538652240,"nautical":1538650320},"set":{"apparent":1538695560,"astronomical":1538614740,"civil":1538697240,"nautical":1538612760}},"timezone":{"name":"America/Chicago","now_in_dst":1,"offset_sec":-18000,"offset_string":-500,"short_name":"CDT"},"what3words":{"words":"serve.last.swing"}},"components":{"ISO_3166-1_alpha-2":"US","_type":"road","country":"United States of America","country_code":"us","road":"S Villa Ave","state":"IL","town":"Villa Park"},"confidence":9,"formatted":"S Villa Ave, Villa Park, IL, United States of America","geometry":{"lat":41.887615,"lng":-87.969234}}],"status":{"code":200,"message":"OK"},"stay_informed":{"blog":"https://blog.opencagedata.com","twitter":"https://twitter.com/opencagedata"},"thanks":"For using an OpenCage Data API","timestamp":{"created_http":"Thu, 04 Oct 2018 20:24:26 GMT","created_unix":1538684666},"total_results":3}