[{"brewery_name":"New District Brewing Company","brewery_link":"https://www.beeradvocate.com/beer/profile/43809/","link":"https://www.beeradvocate.com/beer/profile/43809/209754/","name":"1821 Ale","style_link":"https://www.beeradvocate.com/beer/styles/129/","style_name":"Belgian Saison","abv":"5.50","rating_counts":"7","total_score":"3.42"},{"brewery_name":"New District Brewing Company","brewery_link":"https://www.beeradvocate.com/beer/profile/43809/","link":"https://www.beeradvocate.com/beer/profile/43809/209755/","name":"1821 Dark","style_link":"https://www.beeradvocate.com/beer/styles/80/","style_name":"Baltic Porter","abv":"8.50","rating_counts":"6","total_score":"3.7"},{"brewery_name":"New District Brewing Company","brewery_link":"https://www.beeradvocate.com/beer/profile/43809/","link":"https://www.beeradvocate.com/beer/profile/43809/354247/","name":"Abbey 2 Year Anniversary Dubbel","style_link":"https://www.beeradvocate.com/beer/styles/57/","style_name":"Belgian Dubbel","abv":"7.20","rating_counts":"1","total_score":"3.42"},{"brewery_name":"New District Brewing Company","brewery_link":"https://www.beeradvocate.com/beer/profile/43809/","link":"https://www.beeradvocate.com/beer/profile/43809/365473/","name":"All Your Haze","style_link":"https://www.beeradvocate.com/beer/styles/116/","style_name":"American IPA","abv":"5.50","rating_counts":"1","total_score":"4.64"},{"brewery_name":"New District Brewing Company","brewery_link":"https://www.beeradvocate.com/beer/profile/43809/","link":"https://www.beeradvocate.com/beer/profile/43809/209757/","name":"American Strong Ale","style_link":"https://www.beeradvocate.com/beer/styles/78/","style_name":"American Strong Ale","abv":"7.50","rating_counts":"0","total_score":"0"},{"brewery_name":"New District Brewing Company","brewery_link":"https://www.beeradvocate.com/beer/profile/43809/","link":"https://www.beeradvocate.com/beer/profile/43809/309966/","name":"Auslander Festbier","style_link":"https://www.beeradvocate.com/beer/styles/29/","style_name":"German Märzen / Oktoberfest","abv":"8.00","rating_counts":"0","total_score":"0"},{"brewery_name":"New District Brewing Company","brewery_link":"https://www.beeradvocate.com/beer/profile/43809/","link":"https://www.beeradvocate.com/beer/profile/43809/209756/","name":"Bury The Past ESB","style_link":"https://www.beeradvocate.com/beer/styles/66/","style_name":"English Extra Special / Strong Bitter (ESB)","abv":"5.50","rating_counts":"2","total_score":"3.68"},{"brewery_name":"New District Brewing Company","brewery_link":"https://www.beeradvocate.com/beer/profile/43809/","link":"https://www.beeradvocate.com/beer/profile/43809/264805/","name":"Call To Action","style_link":"https://www.beeradvocate.com/beer/styles/116/","style_name":"American IPA","abv":"8.00","rating_counts":"5","total_score":"2.7"},{"brewery_name":"New District Brewing Company","brewery_link":"https://www.beeradvocate.com/beer/profile/43809/","link":"https://www.beeradvocate.com/beer/profile/43809/213016/","name":"Chocolate Pilsner","style_link":"https://www.beeradvocate.com/beer/styles/41/","style_name":"German Pilsner","abv":"5.50","rating_counts":"1","total_score":"3.26"},{"brewery_name":"New District Brewing Company","brewery_link":"https://www.beeradvocate.com/beer/profile/43809/","link":"https://www.beeradvocate.com/beer/profile/43809/219586/","name":"Dashes And Dots","style_link":"https://www.beeradvocate.com/beer/styles/116/","style_name":"American IPA","abv":"7.00","rating_counts":"1","total_score":"2.72"},{"brewery_name":"New District Brewing Company","brewery_link":"https://www.beeradvocate.com/beer/profile/43809/","link":"https://www.beeradvocate.com/beer/profile/43809/237388/","name":"ESB V2.0","style_link":"https://www.beeradvocate.com/beer/styles/98/","style_name":"English Bitter","abv":"5.00","rating_counts":"0","total_score":"0"},{"brewery_name":"New District Brewing Company","brewery_link":"https://www.beeradvocate.com/beer/profile/43809/","link":"https://www.beeradvocate.com/beer/profile/43809/213015/","name":"Fashionably Late","style_link":"https://www.beeradvocate.com/beer/styles/72/","style_name":"Pumpkin Beer","abv":"5.50","rating_counts":"0","total_score":"0"},{"brewery_name":"New District Brewing Company","brewery_link":"https://www.beeradvocate.com/beer/profile/43809/","link":"https://www.beeradvocate.com/beer/profile/43809/209759/","name":"Folded Note Pils","style_link":"https://www.beeradvocate.com/beer/styles/40/","style_name":"Bohemian Pilsener","abv":"5.60","rating_counts":"2","total_score":"2.96"},{"brewery_name":"New District Brewing Company","brewery_link":"https://www.beeradvocate.com/beer/profile/43809/","link":"https://www.beeradvocate.com/beer/profile/43809/209761/","name":"Ginger Saison","style_link":"https://www.beeradvocate.com/beer/styles/129/","style_name":"Belgian Saison","abv":"5.70","rating_counts":"5","total_score":"3.16"},{"brewery_name":"New District Brewing Company","brewery_link":"https://www.beeradvocate.com/beer/profile/43809/","link":"https://www.beeradvocate.com/beer/profile/43809/365472/","name":"Gregarious IPA","style_link":"https://www.beeradvocate.com/beer/styles/116/","style_name":"American IPA","abv":"5.80","rating_counts":"1","total_score":"4.62"},{"brewery_name":"New District Brewing Company","brewery_link":"https://www.beeradvocate.com/beer/profile/43809/","link":"https://www.beeradvocate.com/beer/profile/43809/262218/","name":"Infinite Beauty","style_link":"https://www.beeradvocate.com/beer/styles/87/","style_name":"Berliner Weisse","abv":"3.20","rating_counts":"2","total_score":"2.11"},{"brewery_name":"New District Brewing Company","brewery_link":"https://www.beeradvocate.com/beer/profile/43809/","link":"https://www.beeradvocate.com/beer/profile/43809/291799/","name":"Jouett's Ride","style_link":"https://www.beeradvocate.com/beer/styles/86/","style_name":"German Altbier","abv":"5.50","rating_counts":"1","total_score":"3.25"},{"brewery_name":"New District Brewing Company","brewery_link":"https://www.beeradvocate.com/beer/profile/43809/","link":"https://www.beeradvocate.com/beer/profile/43809/219565/","name":"Lost Bog Man","style_link":"https://www.beeradvocate.com/beer/styles/97/","style_name":"American Pale Ale (APA)","abv":"5.50","rating_counts":"3","total_score":"3.35"},{"brewery_name":"New District Brewing Company","brewery_link":"https://www.beeradvocate.com/beer/profile/43809/","link":"https://www.beeradvocate.com/beer/profile/43809/209758/","name":"One's And Zero’s","style_link":"https://www.beeradvocate.com/beer/styles/73/","style_name":"American Brown Ale","abv":"7.50","rating_counts":"3","total_score":"3.41"},{"brewery_name":"New District Brewing Company","brewery_link":"https://www.beeradvocate.com/beer/profile/43809/","link":"https://www.beeradvocate.com/beer/profile/43809/262219/","name":"Potomac Paddleboarder","style_link":"https://www.beeradvocate.com/beer/styles/99/","style_name":"American Blonde Ale","abv":"5.50","rating_counts":"2","total_score":"3.4"},{"brewery_name":"New District Brewing Company","brewery_link":"https://www.beeradvocate.com/beer/profile/43809/","link":"https://www.beeradvocate.com/beer/profile/43809/209760/","name":"Pumpkin Seasonal","style_link":"https://www.beeradvocate.com/beer/styles/72/","style_name":"Pumpkin Beer","abv":"5.50","rating_counts":"0","total_score":"0"},{"brewery_name":"New District Brewing Company","brewery_link":"https://www.beeradvocate.com/beer/profile/43809/","link":"https://www.beeradvocate.com/beer/profile/43809/340490/","name":"Rye Pale Ale","style_link":"https://www.beeradvocate.com/beer/styles/97/","style_name":"American Pale Ale (APA)","abv":"5.50","rating_counts":"2","total_score":"4.33"},{"brewery_name":"New District Brewing Company","brewery_link":"https://www.beeradvocate.com/beer/profile/43809/","link":"https://www.beeradvocate.com/beer/profile/43809/237395/","name":"S. German Lager","style_link":"https://www.beeradvocate.com/beer/styles/30/","style_name":"Vienna Lager","abv":"8.00","rating_counts":"1","total_score":"3.83"},{"brewery_name":"New District Brewing Company","brewery_link":"https://www.beeradvocate.com/beer/profile/43809/","link":"https://www.beeradvocate.com/beer/profile/43809/340492/","name":"Something Malty","style_link":"https://www.beeradvocate.com/beer/styles/161/","style_name":"Irish Red Ale","abv":"4.60","rating_counts":"1","total_score":"3.38"},{"brewery_name":"New District Brewing Company","brewery_link":"https://www.beeradvocate.com/beer/profile/43809/","link":"https://www.beeradvocate.com/beer/profile/43809/262217/","name":"Spotswood's Expedition","style_link":"https://www.beeradvocate.com/beer/styles/149/","style_name":"European Dark Lager","abv":"6.00","rating_counts":"2","total_score":"3.65"},{"brewery_name":"New District Brewing Company","brewery_link":"https://www.beeradvocate.com/beer/profile/43809/","link":"https://www.beeradvocate.com/beer/profile/43809/286918/","name":"Stave Off The Invasion","style_link":"https://www.beeradvocate.com/beer/styles/154/","style_name":"English Pale Ale","abv":"5.50","rating_counts":"1","total_score":"2.78"},{"brewery_name":"New District Brewing Company","brewery_link":"https://www.beeradvocate.com/beer/profile/43809/","link":"https://www.beeradvocate.com/beer/profile/43809/280293/","name":"Street Beer","style_link":"https://www.beeradvocate.com/beer/styles/97/","style_name":"American Pale Ale (APA)","abv":"9.00","rating_counts":"3","total_score":"3.25"},{"brewery_name":"New District Brewing Company","brewery_link":"https://www.beeradvocate.com/beer/profile/43809/","link":"https://www.beeradvocate.com/beer/profile/43809/262221/","name":"Strike A Chord","style_link":"https://www.beeradvocate.com/beer/styles/41/","style_name":"German Pilsner","abv":"5.50","rating_counts":"0","total_score":"0"},{"brewery_name":"New District Brewing Company","brewery_link":"https://www.beeradvocate.com/beer/profile/43809/","link":"https://www.beeradvocate.com/beer/profile/43809/262216/","name":"Summer In November (S.I.N)","style_link":"https://www.beeradvocate.com/beer/styles/97/","style_name":"American Pale Ale (APA)","abv":"9.00","rating_counts":"0","total_score":"0"},{"brewery_name":"New District Brewing Company","brewery_link":"https://www.beeradvocate.com/beer/profile/43809/","link":"https://www.beeradvocate.com/beer/profile/43809/373064/","name":"Summer Peach Wheat Sour","style_link":"https://www.beeradvocate.com/beer/styles/171/","style_name":"American Wild Ale","abv":"?","rating_counts":"1","total_score":"4"},{"brewery_name":"New District Brewing Company","brewery_link":"https://www.beeradvocate.com/beer/profile/43809/","link":"https://www.beeradvocate.com/beer/profile/43809/219569/","name":"The Allies","style_link":"https://www.beeradvocate.com/beer/styles/154/","style_name":"English Pale Ale","abv":"5.80","rating_counts":"5","total_score":"2.55"},{"brewery_name":"New District Brewing Company","brewery_link":"https://www.beeradvocate.com/beer/profile/43809/","link":"https://www.beeradvocate.com/beer/profile/43809/210271/","name":"The Bright Future","style_link":"https://www.beeradvocate.com/beer/styles/85/","style_name":"German Kölsch","abv":"4.50","rating_counts":"2","total_score":"3.33"},{"brewery_name":"New District Brewing Company","brewery_link":"https://www.beeradvocate.com/beer/profile/43809/","link":"https://www.beeradvocate.com/beer/profile/43809/210272/","name":"The First Time","style_link":"https://www.beeradvocate.com/beer/styles/157/","style_name":"American Imperial Stout","abv":"8.50","rating_counts":"2","total_score":"3.52"},{"brewery_name":"New District Brewing Company","brewery_link":"https://www.beeradvocate.com/beer/profile/43809/","link":"https://www.beeradvocate.com/beer/profile/43809/219571/","name":"The Last Dance","style_link":"https://www.beeradvocate.com/beer/styles/69/","style_name":"English Oatmeal Stout","abv":"8.50","rating_counts":"3","total_score":"3.4"},{"brewery_name":"New District Brewing Company","brewery_link":"https://www.beeradvocate.com/beer/profile/43809/","link":"https://www.beeradvocate.com/beer/profile/43809/262220/","name":"The Time Stopper","style_link":"https://www.beeradvocate.com/beer/styles/33/","style_name":"German Maibock","abv":"4.00","rating_counts":"0","total_score":"0"},{"brewery_name":"New District Brewing Company","brewery_link":"https://www.beeradvocate.com/beer/profile/43809/","link":"https://www.beeradvocate.com/beer/profile/43809/280297/","name":"Zeros Experimental","style_link":"https://www.beeradvocate.com/beer/styles/97/","style_name":"American Pale Ale (APA)","abv":"8.50","rating_counts":"2","total_score":"3.34"}]