[{"brewery_name":"Rally King Brewing","brewery_link":"https://www.beeradvocate.com/beer/profile/43883/","link":"https://www.beeradvocate.com/beer/profile/43883/219130/","name":"360ยบ","style_link":"https://www.beeradvocate.com/beer/styles/21/","style_name":"German Helles","abv":"5.25","rating_counts":"0","total_score":"0"},{"brewery_name":"Rally King Brewing","brewery_link":"https://www.beeradvocate.com/beer/profile/43883/","link":"https://www.beeradvocate.com/beer/profile/43883/252479/","name":"Apri-Hop","style_link":"https://www.beeradvocate.com/beer/styles/116/","style_name":"American IPA","abv":"6.40","rating_counts":"1","total_score":"3.71"},{"brewery_name":"Rally King Brewing","brewery_link":"https://www.beeradvocate.com/beer/profile/43883/","link":"https://www.beeradvocate.com/beer/profile/43883/248914/","name":"Cit-ra-licious Grapefruit IPA","style_link":"https://www.beeradvocate.com/beer/styles/116/","style_name":"American IPA","abv":"7.74","rating_counts":"2","total_score":"3.71"},{"brewery_name":"Rally King Brewing","brewery_link":"https://www.beeradvocate.com/beer/profile/43883/","link":"https://www.beeradvocate.com/beer/profile/43883/248915/","name":"Coquina Beach Blonde","style_link":"https://www.beeradvocate.com/beer/styles/99/","style_name":"American Blonde Ale","abv":"6.30","rating_counts":"0","total_score":"0"},{"brewery_name":"Rally King Brewing","brewery_link":"https://www.beeradvocate.com/beer/profile/43883/","link":"https://www.beeradvocate.com/beer/profile/43883/252478/","name":"Keith & Willy","style_link":"https://www.beeradvocate.com/beer/styles/163/","style_name":"Chile Beer","abv":"6.40","rating_counts":"1","total_score":"3.69"},{"brewery_name":"Rally King Brewing","brewery_link":"https://www.beeradvocate.com/beer/profile/43883/","link":"https://www.beeradvocate.com/beer/profile/43883/219137/","name":"King's Lullaby","style_link":"https://www.beeradvocate.com/beer/styles/119/","style_name":"Belgian Dark Ale","abv":"6.40","rating_counts":"0","total_score":"0"},{"brewery_name":"Rally King Brewing","brewery_link":"https://www.beeradvocate.com/beer/profile/43883/","link":"https://www.beeradvocate.com/beer/profile/43883/252473/","name":"Kismet Double IPA","style_link":"https://www.beeradvocate.com/beer/styles/140/","style_name":"American Imperial IPA","abv":"9.00","rating_counts":"1","total_score":"3.73"},{"brewery_name":"Rally King Brewing","brewery_link":"https://www.beeradvocate.com/beer/profile/43883/","link":"https://www.beeradvocate.com/beer/profile/43883/252476/","name":"Lion Thistle","style_link":"https://www.beeradvocate.com/beer/styles/68/","style_name":"Scottish Ale","abv":"5.80","rating_counts":"1","total_score":"3.67"},{"brewery_name":"Rally King Brewing","brewery_link":"https://www.beeradvocate.com/beer/profile/43883/","link":"https://www.beeradvocate.com/beer/profile/43883/248917/","name":"Maibock","style_link":"https://www.beeradvocate.com/beer/styles/33/","style_name":"German Maibock","abv":"6.00","rating_counts":"0","total_score":"0"},{"brewery_name":"Rally King Brewing","brewery_link":"https://www.beeradvocate.com/beer/profile/43883/","link":"https://www.beeradvocate.com/beer/profile/43883/252475/","name":"Peachy Noosey","style_link":"https://www.beeradvocate.com/beer/styles/171/","style_name":"American Wild Ale","abv":"6.10","rating_counts":"1","total_score":"3.56"},{"brewery_name":"Rally King Brewing","brewery_link":"https://www.beeradvocate.com/beer/profile/43883/","link":"https://www.beeradvocate.com/beer/profile/43883/252474/","name":"Problem Child","style_link":"https://www.beeradvocate.com/beer/styles/171/","style_name":"American Wild Ale","abv":"6.10","rating_counts":"1","total_score":"3.53"},{"brewery_name":"Rally King Brewing","brewery_link":"https://www.beeradvocate.com/beer/profile/43883/","link":"https://www.beeradvocate.com/beer/profile/43883/219136/","name":"Prospector's Porridge","style_link":"https://www.beeradvocate.com/beer/styles/69/","style_name":"English Oatmeal Stout","abv":"5.90","rating_counts":"1","total_score":"3.58"},{"brewery_name":"Rally King Brewing","brewery_link":"https://www.beeradvocate.com/beer/profile/43883/","link":"https://www.beeradvocate.com/beer/profile/43883/219132/","name":"Pucker Up","style_link":"https://www.beeradvocate.com/beer/styles/87/","style_name":"Berliner Weisse","abv":"3.80","rating_counts":"0","total_score":"0"},{"brewery_name":"Rally King Brewing","brewery_link":"https://www.beeradvocate.com/beer/profile/43883/","link":"https://www.beeradvocate.com/beer/profile/43883/219138/","name":"Red Scooter","style_link":"https://www.beeradvocate.com/beer/styles/128/","style_name":"American Amber / Red Ale","abv":"5.40","rating_counts":"1","total_score":"3.54"},{"brewery_name":"Rally King Brewing","brewery_link":"https://www.beeradvocate.com/beer/profile/43883/","link":"https://www.beeradvocate.com/beer/profile/43883/248916/","name":"Royal Rassy","style_link":"https://www.beeradvocate.com/beer/styles/73/","style_name":"American Brown Ale","abv":"6.70","rating_counts":"1","total_score":"3.58"},{"brewery_name":"Rally King Brewing","brewery_link":"https://www.beeradvocate.com/beer/profile/43883/","link":"https://www.beeradvocate.com/beer/profile/43883/219134/","name":"Small Hours","style_link":"https://www.beeradvocate.com/beer/styles/149/","style_name":"European Dark Lager","abv":"5.20","rating_counts":"0","total_score":"0"},{"brewery_name":"Rally King Brewing","brewery_link":"https://www.beeradvocate.com/beer/profile/43883/","link":"https://www.beeradvocate.com/beer/profile/43883/289019/","name":"Spectrum","style_link":"https://www.beeradvocate.com/beer/styles/97/","style_name":"American Pale Ale (APA)","abv":"5.00","rating_counts":"1","total_score":"3.69"},{"brewery_name":"Rally King Brewing","brewery_link":"https://www.beeradvocate.com/beer/profile/43883/","link":"https://www.beeradvocate.com/beer/profile/43883/219131/","name":"Straw House","style_link":"https://www.beeradvocate.com/beer/styles/54/","style_name":"Belgian Pale Ale","abv":"5.80","rating_counts":"0","total_score":"0"},{"brewery_name":"Rally King Brewing","brewery_link":"https://www.beeradvocate.com/beer/profile/43883/","link":"https://www.beeradvocate.com/beer/profile/43883/219128/","name":"Surfer Girl","style_link":"https://www.beeradvocate.com/beer/styles/116/","style_name":"American IPA","abv":"7.74","rating_counts":"2","total_score":"3.76"},{"brewery_name":"Rally King Brewing","brewery_link":"https://www.beeradvocate.com/beer/profile/43883/","link":"https://www.beeradvocate.com/beer/profile/43883/219129/","name":"Tanlines","style_link":"https://www.beeradvocate.com/beer/styles/128/","style_name":"American Amber / Red Ale","abv":"5.60","rating_counts":"0","total_score":"0"},{"brewery_name":"Rally King Brewing","brewery_link":"https://www.beeradvocate.com/beer/profile/43883/","link":"https://www.beeradvocate.com/beer/profile/43883/219135/","name":"Zwodder","style_link":"https://www.beeradvocate.com/beer/styles/19/","style_name":"American Barleywine","abv":"12.50","rating_counts":"0","total_score":"0"}]